adafruit_circuitpython_fona-3.0.10.dist-info/licenses/LICENSE
adafruit_fona/__init__.py
adafruit_fona/adafruit_fona.py
adafruit_fona/adafruit_fona_network.py
adafruit_fona/adafruit_fona_socket.py
adafruit_fona/fona_3g.py
adafruit_circuitpython_fona-3.0.10.dist-info/METADATA
adafruit_circuitpython_fona-3.0.10.dist-info/WHEEL
adafruit_circuitpython_fona-3.0.10.dist-info/top_level.txt
adafruit_circuitpython_fona-3.0.10.dist-info/RECORD
