Metadata-Version: 2.4
Name: adafruit-circuitpython-fona
Version: 3.0.10
Summary: CircuitPython library for the Adafruit FONAA
Author-email: Adafruit Industries <circuitpython@adafruit.com>
License: MIT
Project-URL: Homepage, https://github.com/adafruit/Adafruit_CircuitPython_FONA
Keywords: adafruit,blinka,circuitpython,micropython,fona,fona,,cellular
Classifier: Intended Audience :: Developers
Classifier: Topic :: Software Development :: Libraries
Classifier: Topic :: Software Development :: Embedded Systems
Classifier: Topic :: System :: Hardware
Classifier: License :: OSI Approved :: MIT License
Classifier: Programming Language :: Python :: 3
License-File: LICENSE
Requires-Dist: Adafruit-Blinka
Requires-Dist: adafruit-circuitpython-simpleio
Requires-Dist: adafruit-circuitpython-busdevice
Provides-Extra: optional
Dynamic: license-file
